parsomics_plugin_dbcan/__init__.py
parsomics_plugin_dbcan/annotation_type.py
parsomics_plugin_dbcan/file_factory.py
parsomics_plugin_dbcan/parser.py
parsomics_plugin_dbcan/plugin_initializer.py
parsomics_plugin_dbcan/populate.py
parsomics_plugin_dbcan/processor.py
parsomics_plugin_dbcan/validated_file.py
parsomics_plugin_dbcan-1.0.6.dist-info/LICENSE
parsomics_plugin_dbcan-1.0.6.dist-info/METADATA
parsomics_plugin_dbcan-1.0.6.dist-info/WHEEL
parsomics_plugin_dbcan-1.0.6.dist-info/RECORD
