Metadata-Version: 2.3
Name: parsomics-plugin-dbcan
Version: 1.0.6
Summary: A parsomics plugin to populate protein annotations with dbCAN
License: GPLv3
Author: Pedro Sader Azevedo
Author-email: pedro.saderazevedo@lnbr.cnpem.br
Requires-Python: >=3.12,<4.0
Classifier: License :: Other/Proprietary License
Classifier: Programming Language :: Python :: 3
Classifier: Programming Language :: Python :: 3.12
Classifier: Programming Language :: Python :: 3.13
Requires-Dist: parsomics-core (>=4.1.0,<5.0.0)
Requires-Dist: polars (>=1.7.0,<2.0.0)
Requires-Dist: pydantic (>=2.9.1,<3.0.0)
Requires-Dist: sqlalchemy (>=2.0.34,<3.0.0)
Requires-Dist: sqlmodel (>=0.0.22,<0.0.23)
Requires-Dist: timeit-decorator (>=1.1.1,<2.0.0)
